org/__init__.py
org/openbaton/__init__.py
org/openbaton/plugin/__init__.py
org/openbaton/plugin/sdk/__init__.py
org/openbaton/plugin/sdk/abstracts.py
org/openbaton/plugin/sdk/catalogue.py
org/openbaton/plugin/sdk/utils.py
org/openbaton/plugin/sdk/vim.py
python_plugin_sdk-6.0.1.dist-info/METADATA
python_plugin_sdk-6.0.1.dist-info/RECORD
python_plugin_sdk-6.0.1.dist-info/WHEEL
python_plugin_sdk-6.0.1.dist-info/top_level.txt
tests/__init__.py
tests/simple_test.py
