Metadata-Version: 2.1
Name: python-plugin-sdk
Version: 6.0.1
Summary: The Python version of the Open Baton plugin-sdk
Home-page: http://openbaton.github.io/
Author: Open Baton
Author-email: dev@openbaton.org
License: Apache 2
Keywords: python plugin nfvo open baton openbaton sdk
Platform: UNKNOWN
Classifier: Development Status :: 5 - Production/Stable
Classifier: Intended Audience :: Developers
Classifier: Topic :: Software Development :: Build Tools
Classifier: Topic :: Utilities
Classifier: License :: OSI Approved :: Apache Software License
Requires-Dist: pika
